{"created_at": "Thu Apr 11 15:51:23 +0000 2019", "location": null, "text": "TEST_PLACE: 0ec3aaa4-b735-4940-8e66-c3207f4bcca9"}
{"created_at": "Thu Apr 11 15:51:25 +0000 2019", "location": "Oakland", "text": "Birthday comin up in a week\ud83e\udd29"}
{"created_at": "Thu Apr 11 15:51:26 +0000 2019", "location": "San Francisco", "text": "@al_isonaboat Pro-plague"}
{"created_at": "Thu Apr 11 15:51:33 +0000 2019", "location": "San Jose, CA", "text": "Part two of visiting the Entercom San Francisco place with my broadcasting class yesterday. @ KCBS Radio https://t.co/Sksz5lDfBe"}
{"created_at": "Thu Apr 11 15:51:33 +0000 2019", "location": "san francisco, california", "text": "@MACHETEMAMBO Fuck Safeway"}
{"created_at": "Thu Apr 11 15:51:34 +0000 2019", "location": "Silicon Valley, California", "text": "Nice what a beautiful design I\u2019ll pass on a road test..."}
{"created_at": "Thu Apr 11 15:51:38 +0000 2019", "location": null, "text": "Keeping to this year\u2019s posting of all my finish times.\n\u2022\nFunny how this one doesn\u2019t necessarily seem all the fast,\u2026 https://t.co/ueMqs1h2El"}
{"created_at": "Thu Apr 11 15:51:38 +0000 2019", "location": "San Francisco", "text": "Conformity is the enemy of creativity atelier.crenn\n#incrennible @ Atelier Crenn https://t.co/bMzBHg9m03"}
{"created_at": "Thu Apr 11 15:51:38 +0000 2019", "location": "Porterville, CA", "text": "I hate a liar ."}
{"created_at": "Thu Apr 11 15:51:39 +0000 2019", "location": "San Francisco, CA", "text": "Of course, it was started by #Celtics fans/players."}
{"created_at": "Thu Apr 11 15:51:46 +0000 2019", "location": "Oakland, California", "text": "@rideact Unfortunately, the URL for a particular bus line, direction, and stop isn\u2019t bookmarkable so I can\u2019t return\u2026 https://t.co/69lyTIGAmy"}
{"created_at": "Thu Apr 11 15:51:47 +0000 2019", "location": "SFCA", "text": "@SarahEHBurr @RichardPBurr It will be a reward for all of you...a treat, if you will. \ud83d\ude01 Good doggies!"}
{"created_at": "Thu Apr 11 15:51:47 +0000 2019", "location": null, "text": "TEST_LAT/LON: e13dc1f4-9233-4854-83ff-7907ac63898d"}
{"created_at": "Thu Apr 11 15:51:48 +0000 2019", "location": "worldwide", "text": "\ud83d\udcf7 | #AGFINTour M&amp;G;\n        Los Angeles - April 10 https://t.co/PihUQB4aGs"}
{"created_at": "Thu Apr 11 15:51:48 +0000 2019", "location": null, "text": "@MarkWillard85 @EPCATDork I think the reason these films are even a talking point is because they're coming at us s\u2026 https://t.co/9BL7V8jJFK"}
{"created_at": "Thu Apr 11 15:51:52 +0000 2019", "location": "worldwide", "text": "\ud83d\udcf7 | #AGFINTour M&amp;G;\n        Los Angeles - April 10 #2 https://t.co/9cPjEHIcYG"}
{"created_at": "Thu Apr 11 15:51:53 +0000 2019", "location": "Mexico", "text": "Como siempre apoyando a la comunidad, excelente trabajo! \ud83e\udd13\ud83d\udc4d\ud83c\udffd"}
{"created_at": "Thu Apr 11 15:51:53 +0000 2019", "location": "https://www.teepublic.com/user/agelessgames", "text": "@twitchtvf0rced @MechWarriorF2P @Paul_Inouye @Chris_C_Lowrey @russ_bullock I would think the more information the b\u2026 https://t.co/Dbj83qVarM"}
{"created_at": "Thu Apr 11 15:51:53 +0000 2019", "location": "worldwide", "text": "\ud83d\udcf7 | #AGFINTour M&amp;G;\n        Los Angeles - April 10 #3 https://t.co/ZG2fsWyXLP"}
{"created_at": "Thu Apr 11 15:51:55 +0000 2019", "location": "San Jose, CA", "text": "U know he rapper when he walking around reading a dictionary"}
{"created_at": "Thu Apr 11 15:51:56 +0000 2019", "location": "worldwide", "text": "\ud83d\udcf7 | #AGFINTour M&amp;G;\n        Los Angeles - April 10 #4 https://t.co/zGxYDbVRMn"}
{"created_at": "Thu Apr 11 15:51:58 +0000 2019", "location": "worldwide", "text": "\ud83d\udcf7 | #AGFINTour M&amp;G;\n        Los Angeles - April 10 #5 https://t.co/VcfuZqfY9y"}
{"created_at": "Thu Apr 11 15:52:00 +0000 2019", "location": "Oakland, CA", "text": "I'm fuckin dying!!!\ud83d\ude02\ud83d\ude02\ud83d\ude02"}
{"created_at": "Thu Apr 11 15:52:03 +0000 2019", "location": "Dublin, CA", "text": "Drinking  The Waldos' Special Ale (2019) by @lagunitasbeer @ Amador Lakes Apartments \u2014 https://t.co/uhK5urtAWF"}
{"created_at": "Thu Apr 11 15:52:03 +0000 2019", "location": "San Francisco, CA, USA", "text": "San Francisco :: The Technology 202: This is Ted Cruz's playbook to crack down on Big Tech for alleged anti-conserv\u2026 https://t.co/DZJKM4Rde1"}
{"created_at": "Thu Apr 11 15:52:04 +0000 2019", "location": "Alameda, CA", "text": "\u26a0\ufe0fWARNING\u26a0\ufe0f\nThe following image contains content that may exhibit extreme amounts of cuteness that can brighten you\u2026 https://t.co/xN1JwLErmo"}
{"created_at": "Thu Apr 11 15:52:05 +0000 2019", "location": "Silicon Valley, CA", "text": "@BMCSoftware is proud to be a platinum sponsor at #HDIConf. Come to booth #615 to learn more #BMCHelix.  @ThinkHDI\u2026 https://t.co/vU8g6BTu2q"}
{"created_at": "Thu Apr 11 15:52:06 +0000 2019", "location": "415", "text": "i\u2019m single! till i get ask to be ur girlfriend"}
{"created_at": "Thu Apr 11 15:52:06 +0000 2019", "location": "San Francisco, CA, USA", "text": "San Francisco :: What we know \u2014 and don\u2019t know \u2014 about WikiLeaks, Julian Assange and the 2016 campaign: An overview\u2026 https://t.co/gHb75hcluv"}
{"created_at": "Thu Apr 11 15:52:08 +0000 2019", "location": "Los Angeles, CA", "text": "2- em 2018 fui pro Coachella com uma amigas e as amigas blogueiras famosinhas dela"}
{"created_at": "Thu Apr 11 15:52:08 +0000 2019", "location": null, "text": "@thesnakefarm @TeslaTunnel @Reboticant @timmerenginerd @Synthesized1618 @Tesla Can you explain what 110% YoY growth\u2026 https://t.co/EjNbS5HiMq"}
{"created_at": "Thu Apr 11 15:52:09 +0000 2019", "location": "California, USA", "text": "@_KarateChris @CapStephofWest Nothing guaranteed for Dubs...one injury and we know it could all crumble."}
{"created_at": "Thu Apr 11 15:52:09 +0000 2019", "location": "San Francisco, CA, USA", "text": "San Francisco :: The Daily 202: Julian Assange\u2019s arrest is another aftershock of the 2016 election: Trump\u2019s sister,\u2026 https://t.co/ZU3Z3C8xBD"}
{"created_at": "Thu Apr 11 15:52:10 +0000 2019", "location": "SFCA", "text": "@stephenfry Oh my word, beauty!"}
{"created_at": "Thu Apr 11 15:52:11 +0000 2019", "location": "San Francisco, CA, USA", "text": "San Francisco :: Pelosi slams Trump\u2019s Fed picks as \u2018totally unsuited, unqualified\u2019: Pelosi made the remarks hours b\u2026 https://t.co/iAf13S3jf6"}
{"created_at": "Thu Apr 11 15:52:12 +0000 2019", "location": "San Francisco, CA, USA", "text": "San Francisco :: Former White House official accused in security clearance dispute to face House committee: Carl Kl\u2026 https://t.co/krcfd6yHNi"}
{"created_at": "Thu Apr 11 15:52:13 +0000 2019", "location": "Manchester, uk & Bermuda", "text": "@PeterBoneUK If only,  but parasites don\u2019t go on their own accord,  they have to be removed."}
{"created_at": "Thu Apr 11 15:52:14 +0000 2019", "location": "San Francisco, CA, USA", "text": "San Francisco :: Digging into the details of the indictment against Julian Assange: Explaining everything from cons\u2026 https://t.co/htWj85BBoK"}
{"created_at": "Thu Apr 11 15:52:15 +0000 2019", "location": "San Francisco, CA, USA", "text": "San Francisco :: Trump shares an inaccurate graphic on Twitter that overstates his job approval by 12 points: The p\u2026 https://t.co/jw10DHhxV0"}
{"created_at": "Thu Apr 11 15:52:16 +0000 2019", "location": "REAL RICHMOND,CA", "text": "\ud83e\udd7a\ud83e\udd7a\ud83e\udd7a\u2764\ufe0f\u2764\ufe0f"}
{"created_at": "Thu Apr 11 15:52:16 +0000 2019", "location": "San Francisco, CA, USA", "text": "San Francisco :: Michael Avenatti hit with 36 federal charges, including tax fraud and embezzlement, report says: F\u2026 https://t.co/8M7lyHWYth"}
{"created_at": "Thu Apr 11 15:52:17 +0000 2019", "location": null, "text": "@SenSchumer Hey America. This is the height of hypocrisy. Chuckie is saying no evidence of spying. There was never\u2026 https://t.co/wO2BekAtUC"}
{"created_at": "Thu Apr 11 15:52:18 +0000 2019", "location": "https://www.teepublic.com/user/agelessgames", "text": "@BrioS_BRxV @twitchtvf0rced @MechWarriorF2P @Paul_Inouye @Chris_C_Lowrey @russ_bullock I agree I would like to know that as well"}
{"created_at": "Thu Apr 11 15:52:18 +0000 2019", "location": "San Jose, CA", "text": "Looking to score a job at Flex? You're in luck. Click the link in our bio for the job description and information o\u2026 https://t.co/qhJKLRF1iR"}
{"created_at": "Thu Apr 11 15:52:17 +0000 2019", "location": "San Francisco, CA, USA", "text": "San Francisco :: Who counts as a major Democratic primary candidate? You tell us.: An interactive tool letting you\u2026 https://t.co/psNPEld6Xp"}
{"created_at": "Thu Apr 11 15:52:21 +0000 2019", "location": "San Francisco", "text": "@sonic They are I believe."}
{"created_at": "Thu Apr 11 15:52:21 +0000 2019", "location": null, "text": "@Jerichoooo @reedrodz @TimMaxwell22 @MattGeorgeKHTK Hire Jason Kidd"}
{"created_at": "Thu Apr 11 15:52:24 +0000 2019", "location": "Bay Area", "text": "@sterlingcrispin @hmltn I stopped following the drama a while ago but from what I recall the r/vive mod takes a ver\u2026 https://t.co/mvuNtS1Irw"}
{"created_at": "Thu Apr 11 15:52:24 +0000 2019", "location": "Fayetteville. \ue01d Keller, Texas.", "text": "@dgaines_15 https://t.co/1wtzubWlk3 \ud83d\ude02\ud83d\ude02\ud83d\ude02"}
{"created_at": "Thu Apr 11 15:52:25 +0000 2019", "location": null, "text": "TEST_GEO_Hierarchy: 3712db1b-529b-44a8-ba68-d1355dbf8fa0"}
{"created_at": "Thu Apr 11 15:52:29 +0000 2019", "location": "California, USA", "text": "I\u2019m out of trust to give"}
{"created_at": "Thu Apr 11 15:52:30 +0000 2019", "location": "Palo Alto", "text": "@rabois @shaig I\u2019m surprised it wouldn\u2019t happen, if it\u2019s a top tier investor."}
{"created_at": "Thu Apr 11 15:52:31 +0000 2019", "location": "Los Banos, CA.", "text": "I hate to say this but individual one is right about one thing we do have a national emergency National crisis it's\u2026 https://t.co/VSA5l9M7Ms"}
{"created_at": "Thu Apr 11 15:52:31 +0000 2019", "location": null, "text": "My god daughter is born!!!\ud83e\udd29\ud83e\udd70"}
{"created_at": "Thu Apr 11 15:52:35 +0000 2019", "location": "San Francisco, CA", "text": "@christo4ferris Congratulations Chris!"}
{"created_at": "Thu Apr 11 15:52:35 +0000 2019", "location": "San Francisco, CA, USA", "text": "San Francisco :: Five 2020 candidates will appear at youth-oriented town hall event: Five presidential candidates w\u2026 https://t.co/up1D2zsKT1"}
{"created_at": "Thu Apr 11 15:52:37 +0000 2019", "location": "San Francisco, CA, USA", "text": "San Francisco :: Warren calls for new tax on corporations: Democratic presidential candidate Elizabeth Warren Thurs\u2026 https://t.co/4EwdCE1oTX"}
{"created_at": "Thu Apr 11 15:52:37 +0000 2019", "location": "San Francisco, CA, USA", "text": "San Francisco :: Pelosi: Trump\u2019s Fed picks are 'really dangerous': LEESBURG, Va. \u2014 Speaker Nancy Pelosi on Thursday\u2026 https://t.co/oAeuX5o0Jg"}
{"created_at": "Thu Apr 11 15:52:38 +0000 2019", "location": "Tha Stack by way of Oakland", "text": "@kdaywins https://t.co/FMneGbV9yG"}
{"created_at": "Thu Apr 11 15:52:39 +0000 2019", "location": "San Francisco, CA, USA", "text": "San Francisco :: Avenatti charged with embezzlement, fraud, cheating on taxes: LOS ANGELES \u2014 Attorney Michael Avena\u2026 https://t.co/GxKPxcXqw0"}
{"created_at": "Thu Apr 11 15:52:41 +0000 2019", "location": "San Francisco, CA, USA", "text": "San Francisco :: Kudlow: Fed may not hike interest rates 'in my lifetime': President Donald Trump\u2019s top economic ad\u2026 https://t.co/x0N5zx0hb7"}
{"created_at": "Thu Apr 11 15:52:41 +0000 2019", "location": "Greenwood, CA", "text": "I just watched this and I\u2019m still not sure it happened... a member of Congress genuinely not understanding how coll\u2026 https://t.co/kTGe8XgZDF"}
{"created_at": "Thu Apr 11 15:52:42 +0000 2019", "location": "London", "text": "Getting on that @OnTheLatch hype and started listening to a few episodes last night. One thing is clear -\u2026 https://t.co/Q3zUD52i18"}
{"created_at": "Thu Apr 11 15:52:42 +0000 2019", "location": "San Francisco, CA, USA", "text": "San Francisco :: Trump has whipsawed from praising to knocking Assange and WikiLeaks: Donald Trump has offered prai\u2026 https://t.co/skvSyDl1Wm"}
{"created_at": "Thu Apr 11 15:52:42 +0000 2019", "location": "California", "text": "Student data privacy bill needs slips now. File in support! \u2013 Fred Klonsky - https://t.co/pSTqaO0Svf via @fklonsky https://t.co/HNYb253NAd"}
{"created_at": "Thu Apr 11 15:52:43 +0000 2019", "location": "SF {East} Bay, California", "text": "Absolutely heartbreaking, but beautiful personal narrative on this all-too-short journey of parenthood. I don\u2019t rea\u2026 https://t.co/LxvsBg1inN"}
{"created_at": "Thu Apr 11 15:52:43 +0000 2019", "location": "San Francisco, CA, USA", "text": "San Francisco :: House Democrats launch probe into EPA officials' ties to utilities: The House Energy and Commerce\u2026 https://t.co/F3G6B0g37U"}
{"created_at": "Thu Apr 11 15:52:44 +0000 2019", "location": "San Francisco, CA", "text": "@sheLLbeLL_xo Ecuadorian fashion statement?"}
{"created_at": "Thu Apr 11 15:52:45 +0000 2019", "location": "SF Northbay WC Hollyverse", "text": "I\u2019m available in San Francisco right now! https://t.co/TvegxUHgYJ"}
{"created_at": "Thu Apr 11 15:52:44 +0000 2019", "location": "San Francisco, CA, USA", "text": "San Francisco :: Pence knocks Buttigieg for criticizing him: 'He knows better': Days after South Bend Mayor Pete Bu\u2026 https://t.co/o6p1oedYUs"}
{"created_at": "Thu Apr 11 15:52:45 +0000 2019", "location": "san francisco, ca", "text": "Burning Man is now 80,000+ ?!?! At that point it\u2019s no longer a fringe movement, it\u2019s pretty much mainstream."}
{"created_at": "Thu Apr 11 15:52:46 +0000 2019", "location": "Santa Cruz CA USA Earth", "text": "@AnneRiceAuthor wants to see it. Let that sink in. Doubtless report opens a portal into a world of horror. \ud83e\udddb\u200d\u2640\ufe0f"}
{"created_at": "Thu Apr 11 15:52:49 +0000 2019", "location": null, "text": "TEST_PLACE: 18b204b5-de9b-403b-a0b8-2ad2da99b55a"}
{"created_at": "Thu Apr 11 15:52:50 +0000 2019", "location": "San Jose, CA", "text": "I love @GameOfThrones so much \ud83d\ude2d I\u2019m re-watching it for the third time and it still has me so hooked!!"}
{"created_at": "Thu Apr 11 15:52:50 +0000 2019", "location": null, "text": "@Evan_Rosenfeld @JoyceWhiteVance Just turn the graph upside down and it all makes sense."}
{"created_at": "Thu Apr 11 18:56:12 +0000 2019", "location": "Mare Island, California", "text": "#MyLennarLemon #911goneWild #MAGA #ClearEnough4u #LennarBayArea #LennarHomes #BayArea #MareIsland #VallejoCa\u2026 https://t.co/sfCJUHWInD"}
{"created_at": "Thu Apr 11 18:56:12 +0000 2019", "location": "San Francisco, CA", "text": "@MrPope @hamishbode @yannickbch I don't have to worry about answering Pope's email last anymore because I am finall\u2026 https://t.co/ZfMIOThjf3"}
{"created_at": "Thu Apr 11 18:56:14 +0000 2019", "location": "my atoms pop in and out", "text": "Beautiful dreamer wake onto me, starlight and dewdrops are waiting for thee @ Black Sand Beach, Sausalito CA https://t.co/Tl6RK8CTgF"}
{"created_at": "Thu Apr 11 18:56:20 +0000 2019", "location": "Oxnard, CA", "text": "@stanislasethen1 We will have to collaborate on what books you got and which ones I have .I think it will alw a hug\u2026 https://t.co/m6tiYPPFXa"}
{"created_at": "Thu Apr 11 18:56:23 +0000 2019", "location": "Bay Area, CA", "text": "At this point I live to eat\ud83d\ude02"}
{"created_at": "Thu Apr 11 18:56:28 +0000 2019", "location": "San Leandro, CA", "text": "I know the people who run @TheMasters march to the beat of their own drum, but no coverage until noon PT every day is just horseshit."}
{"created_at": "Thu Apr 11 18:56:30 +0000 2019", "location": "The Bay Area", "text": "Thanks @SIRIUSXM for that new new @pandora Now Station! https://t.co/uaBSAY0G8A"}
{"created_at": "Thu Apr 11 18:56:31 +0000 2019", "location": "Washington DC", "text": "Tech talks with: @ChickfilA, @Dell, @lifeatdeloitte, @facebook, @Intuit, @LinkedIn, @lyft, @salesforce, &amp;\u2026 https://t.co/8a4NEJ3kP4"}
{"created_at": "Thu Apr 11 18:56:32 +0000 2019", "location": "Los Angeles, CA", "text": "Currently 58% of you agree with me that the majority of ties are ugly."}
{"created_at": "Thu Apr 11 18:56:33 +0000 2019", "location": "California", "text": "Big Education Ape: Why can\u2019t Betsy DeVos give a direct answer to a direct question? - The Washington Post -\u2026 https://t.co/x6nNTlX5ca"}
{"created_at": "Thu Apr 11 18:56:34 +0000 2019", "location": "San Jose, CA", "text": "@justinkirkland4 happy birthday to the only person I like on here"}
{"created_at": "Thu Apr 11 18:56:36 +0000 2019", "location": "San Francisco", "text": "Then why did you just vote with only two other Democrats to confirm an oil lobbyist to be Secretary of the Interior\u2026 https://t.co/8vunMzzrPv"}
{"created_at": "Thu Apr 11 18:56:35 +0000 2019", "location": "San Francisco, CA", "text": "This whole time I just assumed LG = life's good and that their big dumb smiling face logo was somehow related to th\u2026 https://t.co/AboCBA8i5h"}
{"created_at": "Thu Apr 11 18:56:40 +0000 2019", "location": "$acrafice $uffer $uccess", "text": "Practice makes perfect like sex"}
{"created_at": "Thu Apr 11 18:56:40 +0000 2019", "location": "San Jose, CA", "text": "this!!!"}
{"created_at": "Thu Apr 11 18:56:41 +0000 2019", "location": "Los Angeles, CA", "text": "@AlexMLeo Nine times a day. At least. \ud83d\ude02"}
{"created_at": "Thu Apr 11 18:56:41 +0000 2019", "location": "sm\u2019s basement", "text": "taeyong: the ONLY MAN EVER https://t.co/xfFojRXYaI"}
{"created_at": "Thu Apr 11 18:56:41 +0000 2019", "location": null, "text": "Another $100 and I'll post a video of my ass clapping for you weak losers. \ud83d\ude02\n\n#findom #finsub #paypig #cuck #worship"}
{"created_at": "Thu Apr 11 18:56:43 +0000 2019", "location": "San Francisco, CA", "text": "@TheNickGeiser I love needing lbs of sarcasm to make it through the day of being a Bay Area sports fan"}
{"created_at": "Thu Apr 11 18:56:45 +0000 2019", "location": "Via Lactea", "text": "@scalzi I\u2019m just going assume Begore Sunrise is on the list in the last spot just because if its title"}
{"created_at": "Thu Apr 11 18:56:48 +0000 2019", "location": "ALH84001", "text": "https://t.co/N4shuTG9q8"}
{"created_at": "Thu Apr 11 18:56:51 +0000 2019", "location": " SF", "text": "@amyikes Shun her"}
{"created_at": "Thu Apr 11 18:56:57 +0000 2019", "location": "sjsu '20", "text": "https://t.co/BinouS01aK"}
{"created_at": "Thu Apr 11 18:59:35 +0000 2019", "location": "Portland, OR", "text": "@AlterViggo Says the person defending an inaccurate factual attack that relied on the comparison of totally differe\u2026 https://t.co/WZFKIpcvuw"}
{"created_at": "Thu Apr 11 18:59:38 +0000 2019", "location": "Sonoma, CA", "text": "Just announced! @BeltaneRanch is offering a Signature Sonoma Valley special Accommodation Package! Packages include\u2026 https://t.co/CpU3dnh0eV"}
{"created_at": "Thu Apr 11 18:59:38 +0000 2019", "location": null, "text": "I want to go to here"}
{"created_at": "Thu Apr 11 18:59:39 +0000 2019", "location": "California", "text": "Big Education Ape: Internal memo contradicts DeVos on using federal money to buy guns for teachers - The Washington\u2026 https://t.co/KAOMHZ0ERJ"}
{"created_at": "Thu Apr 11 18:59:42 +0000 2019", "location": "Bay Area, CA", "text": "@OdmWrites I K R...SHE LOOK SO INNOCENT...Even tho I know she surveying her destruction of cursed toilet paper roll so proudly V_V"}
{"created_at": "Thu Apr 11 18:59:45 +0000 2019", "location": "San Jose, Ca", "text": "These videos man."}
{"created_at": "Thu Apr 11 18:59:54 +0000 2019", "location": "Hayward, CA", "text": "#gsmcon2019 folks. If you are in California please take a minute to see if your community is in this."}
{"created_at": "Fri Apr 12 00:51:59 +0000 2019", "location": "M\u00e9xico", "text": "VIERNES, La Torre: Ser\u00e1 un d\u00eda fuerte, dif\u00edcil y con riesgos. Viviremos situaciones que nos har\u00e1n sentir un gran te\u2026 https://t.co/WJpjGzLmY2"}
{"created_at": "Fri Apr 12 00:52:16 +0000 2019", "location": "so cal", "text": "@mikewilson6238 @andersonDrLJA @FPPTim Where are the 100 kids that were airlifted out of Haiti with the Clinton ent\u2026 https://t.co/PC6iHYr7fe"}
{"created_at": "Fri Apr 12 00:52:46 +0000 2019", "location": null, "text": "2. For, Believers are those who, when Allah is mentioned, feel a tremor in their\nhearts, and when they hear His sig\u2026 https://t.co/wVRi7EUAZh"}
{"created_at": "Fri Apr 12 00:52:49 +0000 2019", "location": "Earth", "text": "5.0 earthquake occurred near southern Mid-Atlantic Ridge at 00:31 UTC! #earthquake https://t.co/MlNm4JoI8X"}
{"created_at": "Fri Apr 12 00:52:52 +0000 2019", "location": null, "text": "#Earthquake M5.0 southern Mid-Atlantic Ridge 12 Apr 00:31 UTC - report/info: \nhttps://t.co/F1kVQ5nl4W"}
{"created_at": "Fri Apr 12 00:52:55 +0000 2019", "location": "Lima, Peru", "text": "#PeruNews Earthquake of magnitude 5.3 shook Pisco this morning #National\n watch video -&gt; https://t.co/MYzZur6FYx https://t.co/BjrZG8VODz"}
{"created_at": "Fri Apr 12 00:53:02 +0000 2019", "location": "Everywhere", "text": "A 5.0 magnitude earthquake occurred in Southern Mid-Atlantic Ridge. Details: https://t.co/HLxvSXE8O4 Map: https://t.co/wizwz0PD7Y"}
{"created_at": "Fri Apr 12 00:53:02 +0000 2019", "location": "951", "text": "cus an earthquake can occur and I ain\u2019t trynna be naked at that point in time lol"}
{"created_at": "Fri Apr 12 01:07:51 +0000 2019", "location": "sc - cbas.garcia", "text": "@lucianamariex3 Lmao b there 5 min \u270c\ud83c\udffd\u270c\ud83c\udffd"}
{"created_at": "Fri Apr 12 01:07:51 +0000 2019", "location": null, "text": "@TorrKhan He just not on a team rii now"}
{"created_at": "Fri Apr 12 01:07:51 +0000 2019", "location": "Kirkland, WA", "text": "\"can't what\" lil Scrappy do @DevilMayCry \"okkk\" @CIA 2006 \"let them win\" &amp;when the 10 yes up? @DeptofDefense \"2 yrs\u2026 https://t.co/sPqyh9Vj7j"}
{"created_at": "Fri Apr 12 01:07:52 +0000 2019", "location": "do not quote rt my art you fu", "text": "https://t.co/otGoDGT3R5"}
{"created_at": "Fri Apr 12 01:07:52 +0000 2019", "location": "The Lakes of Madison, Wis.", "text": "Badger Men on the ground in sunny CA #GoBadgers https://t.co/rzc9vT7PGk"}
{"created_at": "Fri Apr 12 01:07:53 +0000 2019", "location": "Unite States Of America", "text": "Pull Up!! @caliente971 \ud83c\uddf5\ud83c\udde6\n\ud83d\udd25\ud83d\udd25\ud83d\udd25\ud83d\udd25 Flama \ud83d\udd25\ud83d\udd25\ud83d\udd25\ud83d\udd25\n\ud83d\ude80\ud83d\ude80\ud83d\ude80 Bam Ba Ram \ud83d\ude80\ud83d\ude80\ud83d\ude80\nGracias a mi bro @djchinow17  \nControlando dial \ud83d\udcfb\ud83c\udfb5\ud83c\udfb6\u2026 https://t.co/QzyNBZKTwS"}
{"created_at": "Fri Apr 12 01:07:55 +0000 2019", "location": "New York, USA", "text": "Not only do I teach Digital Citizenship #beinternetawesome to 5th graders, but I am also the mother of two preteen\u2026 https://t.co/Lfoww8NiLP"}
{"created_at": "Fri Apr 12 01:07:57 +0000 2019", "location": "Gotham City", "text": "#RalphsCoffee #RalphsRoast #RL #RockefellerCenter #icedcappuccino @ Ralph's Coffee https://t.co/kZWUK1VRkw"}
{"created_at": "Fri Apr 12 01:07:58 +0000 2019", "location": "NO CA", "text": "@Amateurcapper It\u2019s a fair assessment...... imho he goes the \u2018extra mile\u2019 to win sometimes. But that\u2019s just me."}
{"created_at": "Fri Apr 12 01:07:58 +0000 2019", "location": "New York, NY", "text": "I love the name \u201cMadison Square Guardian\u201d!"}
{"created_at": "Fri Apr 12 01:07:58 +0000 2019", "location": "New York, USA", "text": "@JAYVERSACE period \ud83d\udc51"}
{"created_at": "Fri Apr 12 01:07:58 +0000 2019", "location": null, "text": "@clionacronin I agree!!! What a great way to start the day - prayer, pledge and exercise - nothing could ever go wr\u2026 https://t.co/aFLc9cpLiQ"}
{"created_at": "Fri Apr 12 01:07:58 +0000 2019", "location": "Oakland, CA", "text": "If you say @MariahCarey  didnt do any thing for or changed the music industry OH HONEY you're opinion is invalid. S\u2026 https://t.co/FMD3h0zkCW"}
{"created_at": "Fri Apr 12 01:07:59 +0000 2019", "location": "California, USA", "text": "@Kaelikyear @CollectivzdPaki @ModalSevenths nah bruh, the DNC leak was all about rigging the primaries with the hel\u2026 https://t.co/Lp2En7pAuF"}
{"created_at": "Fri Apr 12 01:08:00 +0000 2019", "location": "Connecticut", "text": "This has been the longest Wednesday. https://t.co/DeGWMWKnfF"}
{"created_at": "Fri Apr 12 01:08:02 +0000 2019", "location": "New York, NY", "text": "@AndersonKirstin Thanks for reading the book and discussing it!"}
{"created_at": "Fri Apr 12 01:08:03 +0000 2019", "location": "Los Angeles, CA", "text": "Pink hair don\u2019t care? \ud83d\udc96 https://t.co/QuoCWyYtXy"}
{"created_at": "Fri Apr 12 01:08:04 +0000 2019", "location": "San Francisco, CA", "text": "returnofthealien and connected.california in the shop. These strain guides are looking bananas \u2728\ud83d\udd25\ud83d\ude35 @ GrassRootsSF https://t.co/BIGlUrmZMB"}
{"created_at": "Fri Apr 12 01:08:04 +0000 2019", "location": "New York, USA", "text": "\ud83c\udf0aThread of threads \ud83c\udf0a https://t.co/IeLIAEfjmW"}
{"created_at": "Fri Apr 12 01:08:05 +0000 2019", "location": null, "text": "\ud83d\ude1c"}
{"created_at": "Fri Apr 12 01:08:05 +0000 2019", "location": "New York, NY", "text": "@Headspace yes sleep"}
{"created_at": "Fri Apr 12 01:08:05 +0000 2019", "location": "Brooklyn, NY", "text": "@TrezlySnipes FACTS... they making them all cute shoot too. Shooting hoops! NO thanks. Wait till they start taking people's jobs."}
{"created_at": "Fri Apr 12 01:08:06 +0000 2019", "location": "Nueva York/Boston", "text": "Felt cute, might delete later @ New York, New York https://t.co/4XyCAN0rye"}
{"created_at": "Fri Apr 12 01:08:06 +0000 2019", "location": "California, USA", "text": "No one will admit that tbh, if they say they do they better say they report it."}
{"created_at": "Fri Apr 12 01:08:07 +0000 2019", "location": "NYC", "text": "@ZionMonster2019 I use Uberx 2 times I\u2019ve gone alone"}
{"created_at": "Fri Apr 12 01:08:07 +0000 2019", "location": "New York, USA", "text": "@aremi311 @dlarm4_avi8tor @pnut confirmed this theory \ud83e\udd1f\ud83c\udffb\ud83e\udd18\ud83c\udffb"}
{"created_at": "Fri Apr 12 01:08:07 +0000 2019", "location": "bronx", "text": "https://t.co/JDMjezG7pZ"}
{"created_at": "Fri Apr 12 01:08:09 +0000 2019", "location": null, "text": "TEST_LAT/LON: e60b7b04-f569-409c-b477-88f07ef9e15b"}
{"created_at": "Fri Apr 12 01:08:10 +0000 2019", "location": "Yesler & MLK", "text": "Sometimes I just wanna eat pussy."}
{"created_at": "Fri Apr 12 01:08:11 +0000 2019", "location": "San Jose, CA", "text": "\ud83d\ude02\ud83d\ude02\ud83d\ude02\ud83d\ude02\ud83d\ude02\ud83d\ude02 This guy is a clown \ud83d\ude2d\ud83d\ude02"}
{"created_at": "Fri Apr 12 01:08:11 +0000 2019", "location": "Great River, NY", "text": "@CaliSun34 @TracyCampanella Yes but no one looks at us. We are anonymous men who women walk by each and every day."}
{"created_at": "Fri Apr 12 01:08:11 +0000 2019", "location": null, "text": "Inyo County, California, USA\nML 2.1 (4 min ago)\n1km 36.06\u00b0N 117.69\u00b0W\nApr 12, 2019 01:03:25 UTC\n#earthquake https://t.co/15Q8ed4fwD"}
{"created_at": "Fri Apr 12 01:08:12 +0000 2019", "location": "\ud83c\uddee\ud83c\uddf3New Delhi \u27a1 New York\ud83c\uddfa\ud83c\uddf8", "text": "@aasthaavij classic biswas family no response to avoid conflict narrative"}
{"created_at": "Fri Apr 12 01:08:12 +0000 2019", "location": "California, USA", "text": "@KimFisher4edu I\u2019m Republican and True Christian.  And how a \u201cChristian\u201d could cheer on this serial adulterer, chro\u2026 https://t.co/LILa0jFUjR"}
{"created_at": "Fri Apr 12 01:08:12 +0000 2019", "location": "Guadalajara, Jalisco", "text": "@Umbrellaz_ Jajaja oso mil"}
{"created_at": "Fri Apr 12 01:08:12 +0000 2019", "location": "Bronx, NY", "text": "Y\u2019all gonna be faithful if your bf/gf/husband/wife is in jail?"}
{"created_at": "Fri Apr 12 01:08:12 +0000 2019", "location": "319 37th St Brooklyn, NY 11232", "text": "50 Black Playstation 2 Replacement Cases 14mm $34.95 #FreeShip https://t.co/pzZplNhvT4 #DVD #Cases #Generic https://t.co/TiNWxpEm0g"}
{"created_at": "Fri Apr 12 01:08:13 +0000 2019", "location": "NYC", "text": "he\u2019s just so cute and squishy and i just want to protect him from all the bad things \ud83e\udd7a https://t.co/s0qvDplu6n"}
{"created_at": "Fri Apr 12 01:08:14 +0000 2019", "location": "new york city", "text": "my heart is racing https://t.co/bpHTpChDi6"}
{"created_at": "Fri Apr 12 01:08:15 +0000 2019", "location": "Buffalo News", "text": "Penalty on Denver with 9:13 left in first period and 38 seconds left in UMass penalty. 4 on 4 before UMass PP. Denv\u2026 https://t.co/wsvrvJ0UzM"}
{"created_at": "Fri Apr 12 01:08:16 +0000 2019", "location": "New York, New York", "text": "The Lenora Mattingly Weber 22 Book Collection - Beany Malone &amp; Katie Rose Belford - The full set of LMW magic! The\u2026 https://t.co/lecIGXpZ8k"}
{"created_at": "Fri Apr 12 01:08:16 +0000 2019", "location": "Los Angeles, CA", "text": "After the day I\u2019ve had, I\u2019m ready to murder someone."}
{"created_at": "Fri Apr 12 01:08:17 +0000 2019", "location": "East Harlem, Manhattan", "text": "Hillary: \"I disagreed with many things Bush did, heck, I even disagreed with some things Bill did...\" https://t.co/PEA3I1G5cU"}
{"created_at": "Fri Apr 12 01:08:18 +0000 2019", "location": "Brooklyn, NY", "text": "@WWE I Gotta Secret To Tell You AEW Is Getting A TV Contract &amp; Guess What They Are Gonna Be TV-14 \ud83d\ude01\ud83d\udc4c #RAW #SDLIVE"}
{"created_at": "Fri Apr 12 01:08:17 +0000 2019", "location": "San Francisco, CA", "text": "When ur desperate for tix so u get on  a dating app just for extra luck LMAO https://t.co/2FFMveKP00"}
{"created_at": "Fri Apr 12 01:08:18 +0000 2019", "location": "Los Angeles, CA", "text": "@wolfboy74 @TMNT It\u2019s the BEST"}
{"created_at": "Fri Apr 12 01:08:18 +0000 2019", "location": "Manhattan, NY", "text": "I GET TO SEE ONE OF MY BESTFRIEND\u2019S TOMORROW @cmendiola22 !!! And show him NYC, home away from home. \ud83d\ude0d"}
{"created_at": "Fri Apr 12 01:08:18 +0000 2019", "location": "San Francisco", "text": "@yungjustinrhode Heheh I appreciate you!! \ud83d\udc93"}
{"created_at": "Fri Apr 12 01:08:18 +0000 2019", "location": "North Oakland, CA \u2744\ufe0f", "text": "@laquoiaaaa Are you calling me a fat slob?"}
{"created_at": "Fri Apr 12 01:08:18 +0000 2019", "location": "Brooklyn NY", "text": "I think Jaime will end up smashing Brianne and when Cersei finds out ... https://t.co/IdXWTXl0E0"}
{"created_at": "Fri Apr 12 01:08:21 +0000 2019", "location": "New York City", "text": "We need to give chloe sevigny her flowers.  She deserves"}
{"created_at": "Fri Apr 12 01:08:21 +0000 2019", "location": "New York, USA", "text": "Art \ud83d\uddbc"}
{"created_at": "Fri Apr 12 01:08:22 +0000 2019", "location": "New York, NY", "text": "Not surprised"}
{"created_at": "Fri Apr 12 01:08:22 +0000 2019", "location": null, "text": "@z_e_griffiths @nyhackr @thestevemo @MathArmy @WestPointSOSH @slimbock @m_robinson771 I love it!  What started off\u2026 https://t.co/Q0IaFdEvcG"}
{"created_at": "Fri Apr 12 03:32:46 +0000 2019", "location": "Vancouver, BC", "text": "also: some folks really want us to do something with Kingsgate Mall (I told them we're looking at options!) Plus mo\u2026 https://t.co/H7IgdUpoJ4"}
{"created_at": "Fri Apr 12 03:32:52 +0000 2019", "location": null, "text": "@HillaryClinton This coming from a woman who stole money that belonged to the poor Haitians to rebuild their lives\u2026 https://t.co/ITs2v2prg8"}
{"created_at": "Fri Apr 12 03:33:07 +0000 2019", "location": "Knoxville, TN", "text": "We could not put these concerts on in this magnitude without our community partners. Thanks to @broganfinancial  fo\u2026 https://t.co/CJnRoooJ9Z"}
{"created_at": "Fri Apr 12 03:33:12 +0000 2019", "location": null, "text": "Earthquake hits Yemen to various degrees for each province https://t.co/rQbBzGp5wz"}
{"created_at": "Fri Apr 12 03:33:53 +0000 2019", "location": "Portland, Oregon", "text": "It's been said that during one of the lunar expeditions, they dropped a rocket on the moon, and the seismic reading\u2026 https://t.co/svM0U3oTiR"}
{"created_at": "Fri Apr 12 03:34:01 +0000 2019", "location": "Earth", "text": "USGS reports a M2.3 #earthquake 34km SSW of New Allakaket, Alaska on 4/12/19 @ 3:28:29 UTC https://t.co/ZURDntRPWK #quake"}
{"created_at": "Fri Apr 12 03:34:15 +0000 2019", "location": null, "text": "The whole world knows about the Venezuela\u2019s Health Crisis but, @telesurenglish @AOC @BernieSanders are so ignorant\u2026 https://t.co/xDfFSxwHQB"}
{"created_at": "Fri Apr 12 03:34:18 +0000 2019", "location": "Chicago, IL", "text": "I work as a line cook and I see this being helpful for quick at home or for when my tremor is so terrible I can\u2019t c\u2026 https://t.co/7g0zvKreUs"}
{"created_at": "Fri Apr 12 03:34:19 +0000 2019", "location": "@ObeyAlliance is the goal", "text": "I haven't truely loved with a game since 2013 when I started to play LoL, but @Splitgate changed that. Super fun ga\u2026 https://t.co/lfFDOVLJyj"}
{"created_at": "Fri Apr 12 03:34:55 +0000 2019", "location": "London, UK", "text": "1 of 5 stars to QUAKE by Anastasia Slash https://t.co/zxKuY02KzI"}
{"created_at": "Fri Apr 12 03:38:07 +0000 2019", "location": "New Zealand", "text": "3:35pm Updated - Mag 3.75 - In the water 56 km north-north-east of Te Paepae o Aotea, New Zealand https://t.co/tf6XLm1rCH"}
{"created_at": "Fri Apr 12 03:39:46 +0000 2019", "location": "Washington Heights, Manhattan", "text": "@RepThomasMassie this is a heinous disservice to Americans.  800 kyrs is as far back as the ice goes; today's CO2 is likely higher than last 3-5 Mil years.  It's not about  absolute magnitude of change; it is about the rate, which is ~30x faster than at any time you reference"}
{"created_at": "Fri Apr 12 03:40:04 +0000 2019", "location": null, "text": "2.3 magnitude #earthquake. 34km SSW of New Allakaket, Alaska https://t.co/OwsjYuu9fX"}
{"created_at": "Fri Apr 12 03:40:31 +0000 2019", "location": "Paradise", "text": "@painter_nancy @saletan No they won't, not on this magnitude. I often find that the most liberal neighborhoods have the least tolerance for the homeless, just my observation."}
